[
  {
    "name": "digital_dao_male",
    "img": "",
    "data": {
      "titleName": "Дао Цифры",
      "description": "Сегодня не осталось цивилизованного уголка, где бы не применялись IT-технологии. Но с твоей точки зрения всё это — каменный век. Те, кто называют себя хакерами, вызывают лишь улыбку. Ты не используешь приборы и компьютеры, а общаешься с ними на понятном им языке — языке Цифры. И они тебе помогают. Твой мозг перестроен, чтобы ты мог говорить с ними.<br>Кто-то древний сказал, что любая достаточно развитая технология неотличима от магии. Ты — прямое доказательство этого. Ты видишь истину: весь мир — всего лишь физическая форма информации. Той информации, которая требует подлинного служения, взамен даря безграничные возможности.",
      "origins": {
        "isShow": true,
        "info": {
          "before": "",
          "addLine": ""
        },
        "list": [
                      {
                    "description": "ты пользуешься покровительством старших товарищей. Кого именно? Какое будущее тебе прочат? Почему нелегко следовать их ожиданиям?",
                    "id": "S4GWGQP1",
                    "name": "Верный сын",
                    "sign": "энергичный/уставший"
                },
                {
                    "description": "ты хотел оставить предыдущую жизнь, приняв Дао. Почему? Как прошлое напоминает о себе? Кто именно не даёт тебе покоя?",
                    "id": "BBKWH4AD",
                    "name": "Бегущий от прошлого",
                    "sign": "расчётливый/быстрый"
                },
                {
                    "description": "ты принял Дао не по собственному желанию. Как так вышло? Почему ты чувствуешь себя чужим в обществе себе подобных? Чьего расположения ты ищешь особенно старательно?",
                    "id": "VWGGF05A",
                    "name": "Белая ворона",
                    "sign": "старательный/резкий"
                },
                {
                    "description": "вживление импланта лишило тебя воспоминаний. Как ты к этому относишься? Какой «привет» из прошлого ты получил? От кого?",
                    "id": "V8ZXHL2L",
                    "name": "Потерявший память",
                    "sign": "любопытный/мрачный"
                }    
        ]
      },
      "theme": "Есть ли для меня что-то важное вне цифрового мира?",
      "appearance": [
        {"sort": 1, "key": "p1", "value": "Визор, пронзительный или отрешённый взгляд"},
        {"sort": 2, "key": "p2", "value": "Лысый, дреды или абсолютный хаос на голове"},
        {"sort": 3, "key": "p3", "value": "Неопрятный, цифровые татуировки или нервные жесты"},
        {"sort": 4, "key": "p4", "value": "Измождённый вид, измененная внешность или непонятный пол"}
      ],
      "princips": {
        "title": "Когда ты играешь Дао Цифры, ты...",
        "list": [
          {"sort": 1, "key": "p1", "value": "Общаешься с электроникой."},
          {"sort": 2, "key": "p2", "value": "Погружаешься в цифровую среду глубже кого бы то ни было."},
          {"sort": 3, "key": "p3", "value": "Заставляешь приборы делать удивительное и невозможное."},
          {"sort": 4, "key": "p4", "value": "Чувствуешь себя неуютно, когда рядом нет электроники."}
        ]
      },
      "contacts": [
        {"sort": 1, "key": "c1", "name": "", "value": "Не доверю ему компьютер."},
        {"sort": 2, "key": "c2", "name": "", "value": "Ведёт себя так, будто его коротнуло."},
        {"sort": 3, "key": "c3", "name": "", "value": "Жизнь его грамотно запрограммировала."},
        {"sort": 4, "key": "c4", "name": "", "value": ""},
        {"sort": 5, "key": "c5", "name": "", "value": ""}
      ],
      "clusters": {
        "title": "",
        "isShow": true,
        "list": [
          "empire",
          "federation",
          "independent_worlds",
          "borderland"
        ]
      },
      "starter_kits": {
        "text": "",
        "itemsListUp": [
          
        ],
        "itemsListDown": [
          
        ]
      },
      "consumables": {
        "finance": {
          "current": 2,
          "limit": 5
        },
        "resources": {
          "current": 2,
          "limit": 10
        },
        "income": {
          "current": 0,
          "limit": 3
        }
      },
      "additionals": {

      }
    }
  }
]